commit_dude/__init__.py
commit_dude/__main__.py
commit_dude/cli.py
commit_dude/config.py
commit_dude/llm.py
commit_dude/schemas.py
commit_dude-0.1.1.dist-info/METADATA
commit_dude-0.1.1.dist-info/WHEEL
commit_dude-0.1.1.dist-info/entry_points.txt
commit_dude-0.1.1.dist-info/RECORD
