Metadata-Version: 2.4
Name: commit-dude
Version: 0.1.1
Summary: CLI that generates Conventional Commits from git diffs using LangChain + OpenAI
Requires-Python: >=3.10
Requires-Dist: click>=8.0.0
Requires-Dist: langchain-openai>=0.0.2
Requires-Dist: langchain>=0.1.0
Requires-Dist: pyperclip>=1.8.0
Requires-Dist: python-dotenv>=1.0.0
